divent/__init__.py
divent/__main__.py
divent/bot.py
divent/py.typed
divent/static/css/font-awesome.min.css
divent/static/css/global.css
divent/static/fonts/FontAwesome.otf
divent/static/fonts/fontawesome-webfont.eot
divent/static/fonts/fontawesome-webfont.svg
divent/static/fonts/fontawesome-webfont.ttf
divent/static/fonts/fontawesome-webfont.woff
divent/static/fonts/fontawesome-webfont.woff2
divent/static/fonts/open-sans-v29-latin-regular.woff
divent/static/fonts/open-sans-v29-latin-regular.woff2
divent/static/img/deadlink.png
divent/templates/base.html.j2
divent/templates/error.html.j2
divent/templates/footer.html.j2
divent/templates/guilds.html.j2
divent/templates/index.html.j2
divent/templates/subscribe.html.j2
divent/translations/fr.json
divent-5.1.3.dist-info/WHEEL
divent-5.1.3.dist-info/entry_points.txt
divent-5.1.3.dist-info/METADATA
divent-5.1.3.dist-info/RECORD
