Metadata-Version: 2.4
Name: divent
Version: 5.1.3
Summary: The discord scheduled event calendar generator
Author: Xéfir Destiny
Author-email: Xéfir Destiny <xefir@crystalyx.net>
License-Expression: WTFPL
Requires-Dist: disnake==2.10.2
Requires-Dist: ics==0.8.0.dev0
Requires-Dist: python-dotenv>=1.2.1
Requires-Dist: quart>=0.20.0
Requires-Dist: requests-oauthlib>=2.0.0
Requires-Python: >=3.9, <3.14
Project-URL: Bug, https://git.crystalyx.net/Xefir/Divent/issues
Project-URL: Homepage, https://divent.crystalyx.net/
